arangodol/__init__.py
arangodol/tests/__init__.py
arangodol/tests/base_test.py
arangodol/tests/test_arangodb.py
arangodol-0.0.2.dist-info/LICENSE
arangodol-0.0.2.dist-info/METADATA
arangodol-0.0.2.dist-info/WHEEL
arangodol-0.0.2.dist-info/top_level.txt
arangodol-0.0.2.dist-info/RECORD
