Metadata-Version: 2.1
Name: arangodol
Version: 0.0.2
Summary: ArangoDB with a simple (dict-like or list-like) interface
Home-page: https://github.com/i2mint/arangodol
Author: OtoSense
License: apache-2.0
Keywords: arangoDB,data access
Platform: any
Requires-Dist: dol
Requires-Dist: pyArango
